aiorpc/__init__.py
aiorpc/client.py
aiorpc/connection.py
aiorpc/constants.py
aiorpc/exceptions.py
aiorpc/log.py
aiorpc/server.py
aiorpc/utils.py
tests/__init__.py
tests/test_rpc.py
aiorpc-0.1.7.dist-info/LICENSE
aiorpc-0.1.7.dist-info/METADATA
aiorpc-0.1.7.dist-info/WHEEL
aiorpc-0.1.7.dist-info/top_level.txt
aiorpc-0.1.7.dist-info/RECORD
