Metadata-Version: 2.1
Name: aiorpc
Version: 0.1.7
Summary: A fast RPC library based on asyncio and MessagePack
Home-page: http://github.com/choleraehyq/aiorpc
Author: Cholerae Hu
Author-email: choleraehyq@gmail.com
License: WTFPL
Keywords: rpc,msgpack,messagepack,msgpackrpc,messagepackrpc,asyncio
Platform: UNKNOWN
Classifier: Development Status :: 4 - Beta
Classifier: Intended Audience :: Developers
Classifier: Natural Language :: English
Classifier: Programming Language :: Python
Classifier: Programming Language :: Python :: 3.5
Requires-Dist: msgpack
Requires-Dist: uvloop
